neo4j_transfer/__init__.py
neo4j_transfer/_logger.py
neo4j_transfer/errors.py
neo4j_transfer/models.py
neo4j_transfer/n4j.py
neo4j_transfer-0.2.0.dist-info/LICENSE.txt
neo4j_transfer-0.2.0.dist-info/METADATA
neo4j_transfer-0.2.0.dist-info/WHEEL
neo4j_transfer-0.2.0.dist-info/RECORD
