Metadata-Version: 2.3
Name: neo4j-transfer
Version: 0.2.0
Summary: Tool for transferring select data from one active Neo4j instance to another.
Author: jalakoo
Author-email: jalakoo@gmail.com
Requires-Python: >=3.11,<4.0
Classifier: Programming Language :: Python :: 3
Classifier: Programming Language :: Python :: 3.11
Classifier: Programming Language :: Python :: 3.12
Classifier: Programming Language :: Python :: 3.13
Requires-Dist: neo4j-rust-ext (>=5.28.1.0,<6.0.0.0)
Requires-Dist: pdoc (>=15.0.4,<16.0.0)
Requires-Dist: pydantic (>=2.7.1,<3.0.0)
Requires-Dist: python-dotenv (>=1.1.1,<2.0.0)
